rsbids-0.0.1a6.dist-info/METADATA
rsbids-0.0.1a6.dist-info/WHEEL
rsbids-0.0.1a6.dist-info/license_files/LICENSE.md
rsbids/bidspath.py
rsbids/entry.py
rsbids/exceptions.py
rsbids/py.typed
rsbids/pybids/layout/index.py
rsbids/pybids/layout/layout.py
rsbids/pybids/layout/models.py
rsbids/pybids/layout/writing.py
rsbids/pybids/layout/__init__.py
rsbids/pybids/__init__.py
rsbids/tests/helpers.py
rsbids/tests/strategies.py
rsbids/tests/test_benchmarks.py
rsbids/tests/test_parse.py
rsbids/tests/__init__.py
rsbids/userpath.py
rsbids/_lib.pyi
rsbids/__init__.py
rsbids/__init__.pyi
rsbids/_lib.cp311-win32.pyd
rsbids-0.0.1a6.dist-info/RECORD
