Metadata-Version: 2.3
Name: rsbids
Version: 0.0.1a6
Classifier: Programming Language :: Rust
Classifier: Programming Language :: Python :: Implementation :: CPython
Classifier: Programming Language :: Python :: Implementation :: PyPy
Requires-Dist: typing-extensions >=4.6.0
License-File: LICENSE.md
Requires-Python: >=3.8, <4.0
